{"field": 0.38, "animals": 0.27, "grazing": 0.22, "street": 0.06, "motorcycle": 0.23, "car": 0.36, "green": 0.26, "parked": 0.19, "on": 0.34, "side": 0.13, "road": 0.42, "farm": 0.14, "in": 0.31, "background": 0.08, "cows": 0.08, "driving": 0.17, "down": 0.14, "past": 0.03, "herd": 0.15, "sheep": 0.11, "dirt": 0.01, "some": 0.03, "couple": 0.03, "standing": 0.04, "stop": 0.02, "sign": 0.03, "trees": 0.04, "cattle": 0.06, "houses": 0.01, "cars": 0.05, "shop": 0.01, "front": 0.02, "pasture": 0.06, "grass": 0.05, "fence": 0.03, "man": 0.01, "next": 0.1, "wooden": 0.01, "near": 0.02, "building": 0.03, "top": 0.03, "person": 0.04, "through": 0.01, "highway": 0.01, "lot": 0.04, "blur": 0.01, "large": 0.06, "bunch": 0.02, "cats": 0.01, "sitting": 0.02, "vegetation": 0.01, "lush": 0.02, "forest": 0.02, "driveway": 0.01, "number": 0.02, "fire": 0.01, "hydrant": 0.01, "motorcycles": 0.01, "gravel": 0.01, "house": 0.01, "several": 0.02, "horse": 0.01, "taking": 0.01, "truck": 0.01, "plane": 0.01, "distance": 0.01}