{"blurry": 0.1, "street": 0.1, "green": 0.3, "arrow": 0.02, "sign": 0.02, "large": 0.15, "field": 0.38, "sheep": 0.33, "grazing": 0.28, "on": 0.34, "couple": 0.02, "cows": 0.01, "in": 0.23, "car": 0.38, "driving": 0.25, "down": 0.26, "road": 0.42, "next": 0.14, "herd": 0.41, "cattle": 0.1, "animals": 0.22, "some": 0.01, "building": 0.02, "white": 0.01, "top": 0.02, "farm": 0.05, "dirt": 0.02, "forest": 0.05, "yellow": 0.01, "bus": 0.01, "lush": 0.07, "trees": 0.04, "background": 0.03, "hill": 0.02, "behind": 0.01, "person": 0.02, "standing": 0.03, "horse": 0.02, "family": 0.01, "walking": 0.02, "driveway": 0.01, "dog": 0.03, "scene": 0.01, "cars": 0.04, "motorcycle": 0.06, "fence": 0.02, "taking": 0.01, "side": 0.07, "motorcycles": 0.02, "past": 0.06, "lot": 0.03, "pasture": 0.05, "bunch": 0.01, "parked": 0.1, "grass": 0.02, "near": 0.02, "amount": 0.01, "gravel": 0.01, "hillside": 0.01, "small": 0.03, "town": 0.01, "boat": 0.01, "bushes": 0.01, "tree": 0.02, "middle": 0.01, "grassy": 0.01, "cats": 0.01, "parking": 0.01, "zebras": 0.01, "truck": 0.01}